pysystemair/__init__.py
pysystemair/const.py
pysystemair/models.py
pysystemair/pysystemair.py
pysystemair/registers.py
pysystemair-0.3.21.dist-info/LICENSE
pysystemair-0.3.21.dist-info/WHEEL
pysystemair-0.3.21.dist-info/METADATA
pysystemair-0.3.21.dist-info/RECORD
